Metadata-Version: 1.0
Name: guessgame
Version: 0.1
Summary: Guess Game
Home-page: UNKNOWN
Author: UNKNOWN
Author-email: UNKNOWN
License: UNKNOWN
Platform: UNKNOWN
